LICENSE
MANIFEST.in
setup.cfg
setup.py
rebel/__init__.py
rebel/database.py
rebel/exceptions.py
rebel/sql_builder.py
rebel/transaction.py
rebel.egg-info/PKG-INFO
rebel.egg-info/SOURCES.txt
rebel.egg-info/dependency_links.txt
rebel.egg-info/top_level.txt
rebel/drivers/__init__.py
rebel/drivers/pgsql.py
rebel/drivers/sqlite.py